levy_stable_jax/__init__.py
levy_stable_jax/_cache.py
levy_stable_jax/_generate_data.py
levy_stable_jax/_interp.py
levy_stable_jax/_typing.py
levy_stable_jax/_utils.py
levy_stable_jax/distribution.py
levy_stable_jax/estimation.py
levy_stable_jax/logpdf.npy
levy_stable_jax/pymc.py
levy_stable_jax-0.2.1.dist-info/LICENSE
levy_stable_jax-0.2.1.dist-info/METADATA
levy_stable_jax-0.2.1.dist-info/WHEEL
levy_stable_jax-0.2.1.dist-info/RECORD
