Metadata-Version: 2.1
Name: levy-stable-jax
Version: 0.2.1
Summary: Implementation of the Lévy alpha-stable distributions for Jax.
Home-page: https://github.com/tjhunter/levy-stable-jax
License: Apache 2.0
Keywords: levy,stable,jax,probability,statistics
Author: Tim Hunter
Author-email: tjhunter@cs.stanford.edu
Requires-Python: >=3.10,<3.13
Classifier: License :: Other/Proprietary License
Classifier: Programming Language :: Python :: 3
Classifier: Programming Language :: Python :: 3.10
Classifier: Programming Language :: Python :: 3.11
Classifier: Programming Language :: Python :: 3.12
Provides-Extra: inference
Provides-Extra: pymc
Requires-Dist: jax (>=0.4,<0.5)
Requires-Dist: jaxlib (>=0.4.26,<0.5.0)
Requires-Dist: jaxopt (>=0.8,<0.9) ; extra == "inference"
Requires-Dist: numpy (>=1.19,<2.0)
Requires-Dist: numpyro (>=0.14.0,<0.15.0) ; extra == "pymc"
Requires-Dist: pymc (>=5.13.1,<6.0.0) ; extra == "pymc"
Requires-Dist: scipy (>=1.5,<2.0)
Project-URL: Documentation, https://levy-stable-jax.readthedocs.io/en/latest/
Project-URL: Repository, https://github.com/tjhunter/levy-stable-jax
